setup.py
Scribbler.egg-info/PKG-INFO
Scribbler.egg-info/SOURCES.txt
Scribbler.egg-info/dependency_links.txt
Scribbler.egg-info/entry_points.txt
Scribbler.egg-info/top_level.txt
Scribbler.egg-info/zip-safe
scribbler/__init__.py
scribbler/locator.py
scribbler/scribbler_console.py