Metadata-Version: 1.0
Name: Scribbler
Version: 0.3.0
Summary: Scribbler is a parallel test runner.
Home-page: http://github.com/heynemann/scribbler/tree/master
Author: Bernardo Heynemann
Author-email: heynemann@gmail.com
License: OSI
Keywords: Parallel Testing Python PyUnit
Platform: UNKNOWN
Classifier: Development Status :: 2 - Pre-Alpha
Classifier: Intended Audience :: Developers
Classifier: License :: OSI Approved
Classifier: Natural Language :: English
Classifier: Programming Language :: Python :: 2.5
